Workbook

Sheet Sheet1
A1: FORM NO.16
A2: [See rule 31 (1) (a)]
A3: Part A
A4: Certificate under section 203 of the Income Tax Act, 1961 for tax deducted
A5: at source from income chargeable under the head “ Salaries “
A7: Name and address of the employer | G7: Name and Designation of the employee
A8: I Smart Facitech Private Ltd
A9: 317, 3rd Floor,A/2 , Neelgiri Bldg,
A10: Wadala Truck Terminal Near Wadala RTO,
A11: Mumbai -400037
A12: PAN of the Deducter | D12: TAN of the Deducter | G12: PAN of the Employee
A13: AAKCC4528J | D13: MUMC28808D | G13: {{EMP_PAN}}
A14: TDS Circle where annual | G14: PERIOD | J14: Assessment Year
A15: return / statement under | G15: FROM | I15: TO | J15: 2026-27
A16: section 206 is to be filed | G16: 45748 | I16: 45930
A17: Smmary of amount Paid/credited and tax Deducted at source thereon in respect of the Employee
A18: Quarter(s) | C18: Receipt Numbersof Original Quaterly Statements of TDS Under Sub-Section (3) of Section 200 | F18: Amount Paid cridited | H18: Amount of Tax Deducted (Rs) | K18: Amount of Tax Deposited / Remitted (Rs)
A19: Quarter 1 | K19: 0
A20: Quarter 2 | K20: 0
A21: Quarter 3 | K21: 0
A22: Quarter 4 | K22: 0
A23: Total | F23: 0 | H23: 0 | K23: 0
A24: I.DETAILS TAX DEDUCTED AND DEPOSITED INTO CENTRAL GOVERNMENT ACCOUNT THROUGH BOOK ADJUSTMENT
A25: S.No | B25: Tax Deposited In Respect | E25: Book Identification Number (BIN)
B26: of the deducter | E26: Receipt Numbers of | G26: DDO Serial No in | I26: Date Of Transfer | K26: Status of Maching
C27: (Rs) | E27: Form No.24G | G27: Form No.24G | I27: Form No.24G | K27: with Form.No 24G
I28: (dd/mm/yyyy)
A29: 1
A30: 2
A31: 3
A32: 4
A33: 5
A34: 6
A35: 7
A36: 8
A37: 9
A38: 10
A39: 11
A40: 12
A41: Total (Rs) | B41: 0
A43: II.DETAILS TAX DEDUCTED AND DEPOSITED INTO CENTRAL GOVERNMENT ACCOUNT THROUGH BOOK CHALLANA
A44: S.No | B44: Tax Deposited In Respect | E44: Book Identification Number (CIN)
B45: of the deducter | E45: BRS Code of the | G45: Date on Which | I45: Challana Serial | K45: Status of Maching
C46: (Rs) | E46: Bank Branch | G46: Tax Deposited | I46: Number | K46: with Form.No 24G
G47: (dd/mm/yyyy)
A48: 1
A49: 2
A50: 3
A51: 4
A52: 5
A53: 6
A54: 7
A55: 8
A56: 9
A57: 10
A58: 11
A59: 12
A60: Total (Rs) | B60: 0
A61: Verification
A62: I, | B62: Sheshmani Yadav | E62: Son/Doughter of | G62: Jokhanram | J62: Working In the Capacity Of
A63: Manager - Accounts | D63: do hereby certify that a sum of Rs. | I63: 0 | J63: (in words)
F64: has beeen deducted at source and paid to the credit of the Central Government.
A65: I further certify that the information given above is true and correct based on the book of accounts, documents and TDS Statements, TDS Deposited and other available records.
A67: Notes :
A68: 1. Government deductors to fill information in item I if tax is paid without production of an income-tax challan and in item II if tax .
A69: is paid accompanied by an income-tax challan
A70: 2. Non-Government deductors to fill information in item II.
A71: 3. The deductor shall furnish the address of the Commissioner of Income-tax (TDS) having jurisdiction as regards TDS
A72: statements of the assessee.
A73: 4. If an assessee is employed under one employer only during the year, certificate in Form No. 16 issued for the quarter ending on
A74: 31st March of the financial year shall contain the details of tax deducted and deposited for all the quarters of the financial year.
A75: 5. If an assessee is employed under more than one employer during the year, each of the employers shall issue Part
A76: A of the certificate in Form No. 16 pertaining to the period for which such assessee was employed with each of the employers. | P76: I83 = Gross Salary
A77: Part B (Annexure) of the certificate in Form No.16 may be issued by each of the employers or the last employer at the
A78: option of the assessee.
A79: 6. In items I and II, in column for tax deposited in respect of deductee, furnish total amount of TDS and education cess."
A80: Notes : Part B
A81: DETAILS OF SALARY PAID AND ANY OTHER INCOME AND TAX DEDUCTED
A82: 1. Gross Salary *
B83: ( a ) Salary as per provisions contained in section 17 (1) | I83: =DATA!B2 -> 0
B84: ( b ) Value of perquisites under section 17 (2)
B85: (as per Form No. 12 BA, wherever applicable) | I85: 0
B86: ( c ) Profits in lieu of Salary under section 17 (3)
B87: (as per Form No. 12 BA, wherever applicable) | I87: 0
B88: ( d ) Total | J88: =I83+I85+I87 -> 0
B89: ( e ) Reported total amount of salary received from other employers | J89: 0
I90: =DATA!B2 -> 0
A91: 2. Less : Allowance to the extent exempt under section 10
A92: a)
A93: b)
A94: 3. Balance (1-2) | I94: =DATA!B3 -> 0 | J94: =J88-J93 -> 0
I95: =50000+DATA!B3 -> 50000
A96: 4. Deductions :
B97: (a) Standard deduction | F97: Rs. | G97: 50000 | I97: =I90-I95 -> -50000 | P97: G99= PT Annual
B98: (b) Entertainment allowance | F98: Rs. | G98: 0
B99: (c) Tax on Employment | F99: Rs. | G99: =DATA!B3 -> 0
A100: 5. Aggregate of 4 (a to c) | I100: =G97+G99 -> 50000
I101: =I97+DATA!B5 -> -50000
A102: 6. Income chargeable under the Head ‘Salaries’(3-5) | L102: =J94-I100 -> -50000
A104: 7. Add. : Any other income reported by the employee | L104: 0
...

Sheet __CALC__

Sheet DATA
A1: Field | B1: Value
A2: Gross Salary | B2: 0
A3: Professional Tax | B3: 0
A4: PF Annual | B4: 0
A5: Other Income | B5: 0
A6: Total TDS | B6: 0
A7: Tax Calculated | B7: 0
A8: EMP_NAME
A9: EMP_DESIGNATION
